pytggram/__init__.py
pytggram/client.py
pytggram/dispatcher.py
pytggram/exceptions.py
pytggram/filters.py
pytggram/router.py
pytggram/sync_client.py
pytggram/api/__init__.py
pytggram/api/telegram_api.py
pytggram/database/__init__.py
pytggram/database/connection.py
pytggram/database/crud.py
pytggram/database/models.py
pytggram/handlers/__init__.py
pytggram/handlers/callback_handler.py
pytggram/handlers/handler.py
pytggram/handlers/inline_handler.py
pytggram/handlers/message_handler.py
pytggram/handlers/poll_handler.py
pytggram/methods/__init__.py
pytggram/methods/advanced.py
pytggram/methods/auth.py
pytggram/methods/callbacks.py
pytggram/methods/chats.py
pytggram/methods/inline.py
pytggram/methods/messages.py
pytggram/methods/payments.py
pytggram/plugins/__init__.py
pytggram/plugins/example_plugin.py
pytggram/storage/__init__.py
pytggram/storage/json_storage.py
pytggram/storage/memory_storage.py
pytggram/storage/mongodb_storage.py
pytggram/storage/redis_storage.py
pytggram/types/__init__.py
pytggram/types/callback.py
pytggram/types/chat.py
pytggram/types/inline.py
pytggram/types/keyboard.py
pytggram/types/message.py
pytggram/types/payments.py
pytggram/types/poll.py
pytggram/types/user.py
pytggram/utils/__init__.py
pytggram/utils/decorators.py
pytggram/utils/flood_control.py
pytggram/utils/helpers.py
pytggram/utils/mongodb_helpers.py
pytggram/utils/rate_limiter.py
test_pytggram-1.0.5.dist-info/licenses/LICENSE
tests/__init__.py
tests/test_advanced_bot.py
tests/test_basic_bot.py
tests/test_error_handling.py
tests/test_filters.py
tests/test_handlers.py
tests/test_inline_bot.py
tests/test_keyboard_bot.py
tests/test_mongodb_bot.py
tests/test_payment_bot.py
tests/test_plugins.py
tests/test_rate_limiting.py
tests/test_storage.py
tests/fixtures/__init__.py
tests/fixtures/sample_data.py
test_pytggram-1.0.5.dist-info/METADATA
test_pytggram-1.0.5.dist-info/WHEEL
test_pytggram-1.0.5.dist-info/top_level.txt
test_pytggram-1.0.5.dist-info/RECORD
