Metadata-Version: 2.4
Name: test-pytggram
Version: 1.0.5
Summary: An advanced, easy-to-use Telegram Bot Framework with MongoDB support
Home-page: https://github.com/hasnainkk-07/PyTgGram
Author: Endtrz
Author-email: Endtrz <endtrz@gmail.com>
License: MIT License
Project-URL: Homepage, https://github.com/hasnainkk-07/PyTgGram
Project-URL: Documentation, https://github.com/hasnainkk-07/PyTgGram/wiki
Project-URL: Repository, https://github.com/hasnainkk-07/PyTgGram
Project-URL: Issues, https://github.com/hasnainkk-07/PyTgGram/issues
Keywords: telegram,bot,api,framework,async,mongodb
Classifier: Development Status :: 4 - Beta
Classifier: Intended Audience :: Developers
Classifier: License :: OSI Approved :: MIT License
Classifier: Programming Language :: Python :: 3
Classifier: Programming Language :: Python :: 3.7
Classifier: Programming Language :: Python :: 3.8
Classifier: Programming Language :: Python :: 3.9
Classifier: Programming Language :: Python :: 3.10
Classifier: Programming Language :: Python :: 3.11
Classifier: Operating System :: OS Independent
Classifier: Topic :: Software Development :: Libraries
Classifier: Topic :: Communications :: Chat
Classifier: Topic :: Internet
Requires-Python: >=3.7
License-File: LICENSE
Provides-Extra: dev
Requires-Dist: pytest>=7.0.0; extra == "dev"
Requires-Dist: pytest-asyncio>=0.20.0; extra == "dev"
Requires-Dist: black>=22.0.0; extra == "dev"
Requires-Dist: flake8>=5.0.0; extra == "dev"
Requires-Dist: mypy>=0.991; extra == "dev"
Provides-Extra: docs
Requires-Dist: sphinx>=5.0.0; extra == "docs"
Requires-Dist: sphinx-rtd-theme>=1.0.0; extra == "docs"
Provides-Extra: speed
Requires-Dist: uvloop>=0.17.0; extra == "speed"
Requires-Dist: aiodns>=3.0.0; extra == "speed"
Dynamic: author
Dynamic: home-page
Dynamic: license-file
Dynamic: requires-python
